[
    {
        "filename": "file41.jpg",
        "pos_caption": "A white truck parked on the street and two cars are beside it",
        "neg_caption": "A white crosswalk with a car incoming at some distance apart"
    },
    {
        "filename": "file42.jpg",
        "pos_caption": "A group of people walking down a sidewalk and two cars are parked by the side in front",
        "neg_caption": "A road with many cars incoming and ongoing at a distance apart"
    },
    {
        "filename": "file43.jpg",
        "pos_caption": "A row of parked bikes with a car by the side in the same row",
        "neg_caption": "A road with many cars incoming and ongoing at a distance apart"
    },
    {
        "filename": "file44.jpg",
        "pos_caption": "A black car parked on the side of the road",
        "neg_caption": "A white crosswalk with a car incoming at some distance apart"
    },
    {
        "filename": "file45.jpg",
        "pos_caption": "A bus is driving down a city street with a car by the side hidden by lights, at night",
        "neg_caption": "A car driving crossing in front at night and a bus is driving towards with a car by the side"
    },
    {
        "filename": "file46.jpg",
        "pos_caption": "A man walking past a building with a sign on it, through the footpath",
        "neg_caption": "A bus is driving down a city street with a car by the side hidden by lights, at night"
    },
    {
        "filename": "file47.jpg",
        "pos_caption": "A car driving crossing in front at night and a bus is driving towards with a car by the side",
        "neg_caption": "A group of people walking down a sidewalk and two cars are parked by the side in front"
    },
    {
        "filename": "file48.jpg",
        "pos_caption": "A road with many cars incoming and ongoing at a distance apart",
        "neg_caption": "A man walking past a building with a sign on it, through the footpath"
    },
    {
        "filename": "file49.jpg",
        "pos_caption": "A white crosswalk with a car incoming at some distance apart",
        "neg_caption": "A car is driving just in front with a truck beside it, both are incoming"
    },
    {
        "filename": "file50.jpg",
        "pos_caption": "A car is driving just in front with a truck beside it, both are incoming",
        "neg_caption": "A black car parked on the side of the road"
    }
]